[
    {
        "fields": {
            "date_joined": "2014-09-25T21:06:41.122",
            "email": "",
            "first_name": "",
            "groups": [],
            "is_active": true,
            "is_staff": true,
            "is_superuser": true,
            "last_login": "2015-06-22T15:46:53.177",
            "last_name": "",
            "password": "pbkdf2_sha256$10000$6gmBKh6SncAz$JmPzCe38K51fMMal4Lil0RunPDniM19jdrNCJOyOf7k=",
            "user_permissions": [],
            "username": "mark"
        },
        "model": "auth.user",
        "pk": 1
    }
]
